cw_torch/__init__.py
cw_torch/gamma.py
cw_torch/metric.py
cw_torch-0.4.2.dist-info/LICENSE
cw_torch-0.4.2.dist-info/METADATA
cw_torch-0.4.2.dist-info/WHEEL
cw_torch-0.4.2.dist-info/top_level.txt
cw_torch-0.4.2.dist-info/RECORD
