Metadata-Version: 2.1
Name: cw-torch
Version: 0.4.2
Summary: Implementation of a Cramer-Wold distance in PyTorch
Home-page: https://github.com/EszKnop/cw-torch
Author: EszKnop,
Author-email: eszknop@gmail.com
License: MIT
Keywords: cramerwold cwae lcw autoencoder cramer wold
Classifier: Programming Language :: Python :: 3
Classifier: License :: OSI Approved :: MIT License
Classifier: Operating System :: OS Independent
Requires-Python: >=3.9
License-File: LICENSE
Requires-Dist: torch
